elyby_api/__init__.py
elyby_api/_types.py
elyby_api/api.py
elyby_api/core.py
elyby_api/utils.py
elyby_api-0.1.0.dev0.dist-info/LICENSE
elyby_api-0.1.0.dev0.dist-info/METADATA
elyby_api-0.1.0.dev0.dist-info/WHEEL
elyby_api-0.1.0.dev0.dist-info/RECORD
