Metadata-Version: 2.1
Name: elyby-api
Version: 0.1.0.dev0
Summary: Not official library for convenient interaction with API of Ely.by service (custom skin system for minecraft).
Home-page: https://github.com/TheMade4/elyby-api
License: GPL-3.0 license
Author: TheMade4
Requires-Python: >=3.10,<4.0
Classifier: License :: Other/Proprietary License
Classifier: Programming Language :: Python :: 3
Classifier: Programming Language :: Python :: 3.10
Classifier: Programming Language :: Python :: 3.11
Classifier: Programming Language :: Python :: 3.12
Requires-Dist: pydantic (==2.5.1)
Requires-Dist: requests (==2.31.0)
Project-URL: Repository, https://github.com/TheMade4/elyby-api
